cubicweb_ckeditor/__init__.py
cubicweb_ckeditor/__pkginfo__.py
cubicweb_ckeditor/entities.py
cubicweb_ckeditor/hooks.py
cubicweb_ckeditor/schema.py
cubicweb_ckeditor/views.py
cubicweb_ckeditor/data/ckeditor-config.js
cubicweb_ckeditor/data/initwysiwyg.js
cubicweb_ckeditor/i18n/en.po
cubicweb_ckeditor/i18n/es.po
cubicweb_ckeditor/i18n/fr.po
cubicweb_ckeditor/migration/postcreate.py
cubicweb_ckeditor-0.6.0.dist-info/METADATA
cubicweb_ckeditor-0.6.0.dist-info/WHEEL
cubicweb_ckeditor-0.6.0.dist-info/entry_points.txt
cubicweb_ckeditor-0.6.0.dist-info/top_level.txt
cubicweb_ckeditor-0.6.0.dist-info/RECORD
