Metadata-Version: 2.1
Name: cubicweb-ckeditor
Version: 0.6.0
Summary: WYSIWYG js editor with ckeditor
Home-page: https://forge.extranet.logilab.fr/cubicweb/cubes/cubicweb-ckeditor
Author: LOGILAB S.A. (Paris, FRANCE)
Author-email: contact@logilab.fr
License: LGPL
Classifier: Environment :: Web Environment
Classifier: Framework :: CubicWeb
Classifier: Programming Language :: Python
Classifier: Programming Language :: JavaScript
Requires-Dist: cubicweb <5.0.0,>=4.1.0
Requires-Dist: cubicweb-web <2.0.0,>=1.0.0
